hupwatch/__init__.py
hupwatch/args_parser.py
hupwatch/command.py
hupwatch/service.py
hupwatch-0.0.3.dist-info/DESCRIPTION.rst
hupwatch-0.0.3.dist-info/METADATA
hupwatch-0.0.3.dist-info/RECORD
hupwatch-0.0.3.dist-info/WHEEL
hupwatch-0.0.3.dist-info/entry_points.txt
hupwatch-0.0.3.dist-info/metadata.json
hupwatch-0.0.3.dist-info/top_level.txt
