Metadata-Version: 2.0
Name: hupwatch
Version: 0.0.3
Summary: Simple process supervision agnostic utility for graceful reloading of services
Home-page: https://github.com/swistakm/hupwatch
Author: Michał Jaworski
Author-email: swistakm@gmail.com
License: BSD
Platform: UNKNOWN
Classifier: Development Status :: 4 - Beta
Classifier: Intended Audience :: Developers
Classifier: Intended Audience :: System Administrators
Classifier: Operating System :: POSIX
Classifier: Topic :: System :: Systems Administration
Classifier: Programming Language :: Python
Classifier: Programming Language :: Python :: 2
Classifier: Programming Language :: Python :: 2.7
Classifier: Programming Language :: Python :: 3
Classifier: License :: OSI Approved :: BSD License
